tarea1/lavanderia.v
module Lavanderia (
    input clk,
    input rst,
    input intro_moneda,
    input finalizar_pago,
    output reg SECADO,
    output reg LAVADO,
    output reg LAVADO_PESADO,
    output reg insuficiente
);

reg [3:0] count, verificacion_pago;
reg [3:0] pulse_count; 
reg [1:0] modo;
reg internal_rst;

always @(posedge clk) begin
    // Reset or Internal Reset:
    if (rst || internal_rst) begin
        
        count <= 4'b0;
        verificacion_pago <= 4'b0;
        pulse_count <= 4'b0;
        modo <= 2'b0;
        internal_rst = 0;
        SECADO <= 0;
        LAVADO <= 0;
        LAVADO_PESADO <= 0;
        insuficiente <= 0;

    end
    else begin

        // Contar monedas.
        if (intro_moneda) begin 
            count += 1;
        end
        // Finalizar pago.
        else if (finalizar_pago) begin 

            verificacion_pago[3:0] <= count[3:0];
            pulse_count = 3'b0;
            count <= 4'b0;

            // Pago insuficiente/incorrecto:
            if (count != 4'b11 && count != 4'b100 && count != 4'b1001 && count != 0) begin
                insuficiente = 1;
            end

        end
    end

    // Logica para senal de Modo en el flanco positivo:
    if (SECADO) begin
        SECADO = !SECADO;
        pulse_count += 1;
    end
    else if (LAVADO) begin
        LAVADO = !LAVADO;
        pulse_count += 1;
    end
    else if (LAVADO_PESADO) begin
        LAVADO_PESADO = !LAVADO_PESADO;
        pulse_count += 1;
    end

    // Terminar senal de Modo y mandar reset interno.
    if (pulse_count >= 4'b1000) begin
        pulse_count <= 0;
        modo <= 0;
        internal_rst <= 1;
    end
end


always @(negedge clk) begin

    // Pago insuficiente/incompleto:
    if (insuficiente) begin
        internal_rst <= 1;
    end
    // Modo Secado:
    if (verificacion_pago == 4'b0011) begin
        SECADO <= 1;
        modo <= 2'b01; // Almacenar modo SECADO.
        verificacion_pago = 0;  
    end
    // Modo Lavado:
    else if (verificacion_pago == 4) begin
        LAVADO <= 1;
        modo <= 2'b10; // Almacenar modo LAVADO. 
        verificacion_pago = 0;
    end
    // Modo Lavado Pesado:
    else if (verificacion_pago == 9) begin
        LAVADO_PESADO <= 1;
        modo <= 2'b11; // Almacenar modo LAVADO_PESADO.
        verificacion_pago = 0;
    end

    // Logica para senal de Modo en el flanco negativo:
    if (pulse_count > 3'b0) begin
        if (modo == 2'b01) begin
            SECADO = !SECADO;
            pulse_count += 1;
        end
        else if (modo == 2'b10)begin
            LAVADO = !LAVADO;
            pulse_count += 1;
        end
        else if (modo == 2'b11) begin
            LAVADO_PESADO = !LAVADO_PESADO;
            pulse_count += 1;
        end
    end
end

endmodule

tarea1/tester.v
`timescale 1s/1s

module tester(

    output reg clk,
    output reg rst, 
    output reg intro_moneda,
    output reg finalizar_pago,
    input SECADO, LAVADO, LAVADO_PESADO,
    input insuficiente);

    // Instancia del modulo Lavanderia.
    Lavanderia lavanderia(
        .clk(clk),
        .rst(rst),
        .intro_moneda(intro_moneda),
        .finalizar_pago(finalizar_pago),
        .SECADO(SECADO),
        .LAVADO(LAVADO),
        .LAVADO_PESADO(LAVADO_PESADO),
        .insuficiente(insuficiente)
    );

    // Generacion de la señal de reloj.
    always #5 clk = !clk;

    // Pruebas:
    initial begin
        
        // Inicialización.
        clk = 0;
        rst = 1;
        intro_moneda = 0;
        finalizar_pago = 0;

        #10 rst = 0;  // Fin del reset

        // Test 1: SECADO (3 monedas)
        #10
        repeat (6) begin
            #5 intro_moneda = !intro_moneda;
        end
        finalizar_pago = 1;
        #10 finalizar_pago = 0;

        #100

        // Test 2: LAVADO (4 monedas)
        #10
        repeat (8) begin
            #5 intro_moneda = !intro_moneda;
        end
        finalizar_pago = 1;
        #10 finalizar_pago = 0;

        #100

        // Test 3: LAVADO_PESADO (9 monedas)
        #10
        repeat (18) begin
            #5 intro_moneda = !intro_moneda;
        end
         finalizar_pago = 1;
        #10 finalizar_pago = 0;

        #100

        // Test 4: Monedas insuficientes (5 monedas)
        #10
        repeat (10) begin
            #5 intro_moneda = !intro_moneda;
        end
        finalizar_pago = 1;
        #10 finalizar_pago = 0;

        #50 $finish;
    end
    
endmodule

tarea1/testbench.v
`include "lavanderia.v"
`include "tester.v"

module testbench;

    wire clk, rst, intro_moneda, finalizar_pago;
    wire SECADO, LAVADO, LAVADO_PESADO, insuficiente;

    // Instancia del modulo Lavanderia.
    Lavanderia lavanderia(
        .clk(clk),
        .rst(rst),
        .intro_moneda(intro_moneda),
        .finalizar_pago(finalizar_pago),
        .SECADO(SECADO),
        .LAVADO(LAVADO),
        .LAVADO_PESADO(LAVADO_PESADO),
        .insuficiente(insuficiente)
    );

    // Instancia del modulo tester.
    tester test(
        .clk(clk),
        .rst(rst),
        .intro_moneda(intro_moneda),
        .finalizar_pago(finalizar_pago),
        .SECADO(SECADO),
        .LAVADO(LAVADO),
        .LAVADO_PESADO(LAVADO_PESADO),
        .insuficiente(insuficiente)
        
    );

    // Generar las ondas y visualizar en gtkwave.
    initial begin
        $dumpfile("tb.vcd");
        $dumpvars;
    end

    // Mostrar salidas en la terminal.
    always @(posedge clk) begin
       if (SECADO || LAVADO || LAVADO_PESADO || insuficiente) begin
            $display("SECADO: %b,\n LAVADO: %b,\n LAVADO_PESADO: %b\n, insuficiente: %b\n\n",SECADO, LAVADO, LAVADO_PESADO, insuficiente);
       end 
    end

endmodule

tarea1/tb.vcd
$date
	Tue Apr 16 18:45:17 2024
$end
$version
	Icarus Verilog
$end
$timescale
	1s
$end
$scope module testbench $end
$var wire 1 ! LAVADO $end
$var wire 1 " LAVADO_PESADO $end
$var wire 1 # SECADO $end
$var wire 1 $ insuficiente $end
$var wire 1 % rst $end
$var wire 1 & intro_moneda $end
$var wire 1 ' finalizar_pago $end
$var wire 1 ( clk $end
$scope module lavanderia $end
$var wire 1 % rst $end
$var wire 1 & intro_moneda $end
$var wire 1 ' finalizar_pago $end
$var wire 1 ( clk $end
$var reg 1 ) LAVADO $end
$var reg 1 * LAVADO_PESADO $end
$var reg 1 + SECADO $end
$var reg 4 , count [3:0] $end
$var reg 1 - insuficiente $end
$var reg 1 . internal_rst $end
$var reg 2 / modo [1:0] $end
$var reg 4 0 pulse_count [3:0] $end
$var reg 4 1 verificacion_pago [3:0] $end
$upscope $end
$scope module test $end
$var wire 1 ! LAVADO $end
$var wire 1 " LAVADO_PESADO $end
$var wire 1 # SECADO $end
$var wire 1 $ insuficiente $end
$var reg 1 ( clk $end
$var reg 1 ' finalizar_pago $end
$var reg 1 & intro_moneda $end
$var reg 1 % rst $end
$scope module lavanderia $end
$var wire 1 ( clk $end
$var wire 1 ' finalizar_pago $end
$var wire 1 & intro_moneda $end
$var wire 1 % rst $end
$var reg 1 2 LAVADO $end
$var reg 1 3 LAVADO_PESADO $end
$var reg 1 4 SECADO $end
$var reg 4 5 count [3:0] $end
$var reg 1 6 insuficiente $end
$var reg 1 7 internal_rst $end
$var reg 2 8 modo [1:0] $end
$var reg 4 9 pulse_count [3:0] $end
$var reg 4 : verificacion_pago [3:0] $end
$upscope $end
$upscope $end
$upscope $end
$enddefinitions $end
#0
$dumpvars
bx :
bx 9
bx 8
x7
x6
bx 5
x4
x3
x2
bx 1
bx 0
bx /
x.
x-
bx ,
x+
x*
x)
0(
0'
0&
1%
x$
x#
x"
x!
$end
#5
0$
0-
0"
0*
0!
0)
0#
0+
b0 /
b0 0
b0 1
b0 ,
06
03
02
04
b0 8
b0 9
b0 :
b0 5
0.
07
1(
#10
0(
0%
#15
1(
#20
0(
#25
b1 ,
b1 5
1(
1&
#30
0(
0&
#35
b10 5
b10 ,
1(
1&
#40
0(
0&
#45
b11 ,
b11 5
1(
1&
#50
0(
1'
0&
#55
b0 5
b11 :
b0 ,
b11 1
1(
#60
b1 /
1+
b1 8
1#
14
b0 1
b0 :
0(
0'
#65
b1 0
0+
b1 9
0#
04
1(
#70
b10 9
14
b10 0
1#
1+
0(
#75
b11 9
04
b11 0
0#
0+
1(
#80
b100 0
1+
b100 9
1#
14
0(
#85
b101 0
0+
b101 9
0#
04
1(
#90
b110 9
14
b110 0
1#
1+
0(
#95
b111 9
04
b111 0
0#
0+
1(
#100
b1000 0
1+
b1000 9
1#
14
0(
#105
1.
b0 /
17
b0 8
b0 0
0+
b0 9
0#
04
1(
#110
0(
#115
07
0.
1(
#120
0(
#125
1(
#130
0(
#135
1(
#140
0(
#145
1(
#150
0(
#155
1(
#160
0(
#165
1(
#170
0(
#175
b1 5
b1 ,
1(
1&
#180
0(
0&
#185
b10 ,
b10 5
1(
1&
#190
0(
0&
#195
b11 5
b11 ,
1(
1&
#200
0(
0&
#205
b100 ,
b100 5
1(
1&
#210
0(
1'
0&
#215
b0 5
b100 :
b0 ,
b100 1
1(
#220
b10 /
1)
b10 8
1!
12
b0 1
b0 :
0(
0'
#225
b1 0
0)
b1 9
0!
02
1(
#230
b10 9
12
b10 0
1!
1)
0(
#235
b11 9
02
b11 0
0!
0)
1(
#240
b100 0
1)
b100 9
1!
12
0(
#245
b101 0
0)
b101 9
0!
02
1(
#250
b110 9
12
b110 0
1!
1)
0(
#255
b111 9
02
b111 0
0!
0)
1(
#260
b1000 0
1)
b1000 9
1!
12
0(
#265
1.
b0 /
17
b0 8
b0 0
0)
b0 9
0!
02
1(
#270
0(
#275
07
0.
1(
#280
0(
#285
1(
#290
0(
#295
1(
#300
0(
#305
1(
#310
0(
#315
1(
#320
0(
#325
1(
#330
0(
#335
b1 5
b1 ,
1(
1&
#340
0(
0&
#345
b10 ,
b10 5
1(
1&
#350
0(
0&
#355
b11 5
b11 ,
1(
1&
#360
0(
0&
#365
b100 ,
b100 5
1(
1&
#370
0(
0&
#375
b101 5
b101 ,
1(
1&
#380
0(
0&
#385
b110 ,
b110 5
1(
1&
#390
0(
0&
#395
b111 5
b111 ,
1(
1&
#400
0(
0&
#405
b1000 ,
b1000 5
1(
1&
#410
0(
0&
#415
b1001 5
b1001 ,
1(
1&
#420
0(
1'
0&
#425
b0 ,
b1001 1
b0 5
b1001 :
1(
#430
b11 8
13
b11 /
1"
1*
b0 :
b0 1
0(
0'
#435
b1 9
03
b1 0
0"
0*
1(
#440
b10 0
1*
b10 9
1"
13
0(
#445
b11 0
0*
b11 9
0"
03
1(
#450
b100 9
13
b100 0
1"
1*
0(
#455
b101 9
03
b101 0
0"
0*
1(
#460
b110 0
1*
b110 9
1"
13
0(
#465
b111 0
0*
b111 9
0"
03
1(
#470
b1000 9
13
b1000 0
1"
1*
0(
#475
17
b0 8
1.
b0 /
b0 9
03
b0 0
0"
0*
1(
#480
0(
#485
0.
07
1(
#490
0(
#495
1(
#500
0(
#505
1(
#510
0(
#515
1(
#520
0(
#525
1(
#530
0(
#535
1(
#540
0(
#545
b1 ,
b1 5
1(
1&
#550
0(
0&
#555
b10 5
b10 ,
1(
1&
#560
0(
0&
#565
b11 ,
b11 5
1(
1&
#570
0(
0&
#575
b100 5
b100 ,
1(
1&
#580
0(
0&
#585
b101 ,
b101 5
1(
1&
#590
0(
1'
0&
#595
b0 5
b101 :
b0 ,
b101 1
16
1$
1-
1(
#600
1.
17
0(
0'
#605
0-
b0 1
0$
06
b0 :
0.
07
1(
