tarea1_mod/lavanderia.v
module Lavanderia (
    input clk,
    input rst,
    input intro_moneda,
    input finalizar_pago,
    output reg SECADO,
    output reg LAVADO,
    output reg LAVADO_PESADO,
    output reg insuficiente
);

reg [3:0] count;
reg [1:0] state;

// State definitions
localparam IDLE = 2'b00;
localparam COUNTING = 2'b01;
localparam VERIFY = 2'b10;

// State transition and counting logic
always @(posedge clk) begin
    if (rst) begin
        count <= 0;
        state <= IDLE;
        SECADO <= 0;
        LAVADO <= 0;
        LAVADO_PESADO <= 0;
        insuficiente <= 0;
    end
    else begin
        case (state)
            IDLE: begin
                if (intro_moneda) begin
                    state <= COUNTING;
                    count <= count + 1;
                end
            end
            COUNTING: begin
                if (intro_moneda) begin
                    count <= count + 1;
                end
                if (finalizar_pago) begin
                    state <= VERIFY;
                end
            end
            VERIFY: begin
                if (count == 3) begin
                    SECADO <= 1;
                    #30; // Pulse duration for SECADO
                    SECADO <= 0;
                end
                else if (count == 4) begin
                    LAVADO <= 1;
                    #40; // Pulse duration for LAVADO
                    LAVADO <= 0;
                end
                else if (count == 9) begin
                    LAVADO_PESADO <= 1;
                    #90; // Pulse duration for LAVADO_PESADO
                    LAVADO_PESADO <= 0;
                end
                else begin
                    insuficiente <= 1;
                    #10; // Insufficient pulse duration
                    insuficiente <= 0;
                end
                count <= 0; // Resetting the coin count after each transaction
                state <= IDLE; // Returning to IDLE state
            end
        endcase
    end
end

endmodule

tarea1_mod/tester.v
`timescale 1ns/1ns

module tester(

    output reg clk,
    output reg rst, 
    output reg intro_moneda,
    output reg finalizar_pago,
    input SECADO, LAVADO, LAVADO_PESADO,
    input insuficiente);

    // Instancia del módulo Lavanderia
    Lavanderia lavanderia(
        .clk(clk),
        .rst(rst),
        .intro_moneda(intro_moneda),
        .finalizar_pago(finalizar_pago),
        .SECADO(SECADO),
        .LAVADO(LAVADO),
        .LAVADO_PESADO(LAVADO_PESADO),
        .insuficiente(insuficiente)
    );

    // Generación de la señal de reloj
    always #5 clk = !clk;

    // Procedimiento de prueba
    initial begin
        //$monitor($time, " clk=%b rst=%b intro_moneda=%b finalizar_pago=%b SECADO=%b LAVADO=%b LAVADO_PESADO=%b insuficiente=%b",
        //         clk, rst, intro_moneda, finalizar_pago, SECADO, LAVADO, LAVADO_PESADO, insuficiente);

        // Inicialización
        clk = 0;
        rst = 1;
        intro_moneda = 0;
        finalizar_pago = 0;

        #10 rst = 0;  // Fin del reset

        // Test 1: SECADO (3 monedas)
        #10
        repeat (6) begin
            #5 intro_moneda = !intro_moneda;
        end

        finalizar_pago = 1;
        #10 finalizar_pago = 0;

        #50

        // // Test 2: LAVADO (4 monedas)
        // #10
        // repeat (8) begin
        //     #5 intro_moneda = !intro_moneda;
        // end
        // #10 finalizar_pago = 1;
        // #10 finalizar_pago = 0;

        // #50

        // Test 3: LAVADO_PESADO (9 monedas)
        #10
        repeat (18) begin
            #5 intro_moneda = !intro_moneda;
        end
         finalizar_pago = 1;
        #10 finalizar_pago = 0;

        #50

        // Test 4: Monedas insuficientes (2 monedas)
        #10
        repeat (4) begin
            #5 intro_moneda = !intro_moneda;
        end
        finalizar_pago = 1;
        #10 finalizar_pago = 0;

        #50 $finish;
    end
    
endmodule

tarea1/testbench.v
`include "lavanderia.v"
`include "tester.v"

module testbench;

    wire clk, rst, intro_moneda, finalizar_pago;
    wire SECADO, LAVADO, LAVADO_PESADO, insuficiente;

    // Instancia del modulo Lavanderia.
    Lavanderia lavanderia(
        .clk(clk),
        .rst(rst),
        .intro_moneda(intro_moneda),
        .finalizar_pago(finalizar_pago),
        .SECADO(SECADO),
        .LAVADO(LAVADO),
        .LAVADO_PESADO(LAVADO_PESADO),
        .insuficiente(insuficiente)
    );

    // Instancia del modulo tester.
    tester test(
        .clk(clk),
        .rst(rst),
        .intro_moneda(intro_moneda),
        .finalizar_pago(finalizar_pago),
        .SECADO(SECADO),
        .LAVADO(LAVADO),
        .LAVADO_PESADO(LAVADO_PESADO),
        .insuficiente(insuficiente)
        
    );

    // Generar las ondas y visualizar en gtkwave.
    initial begin
        $dumpfile("tb.vcd");
        $dumpvars;
    end

    // Mostrar salidas en la terminal.
    always @(posedge clk) begin
       if (SECADO || LAVADO || LAVADO_PESADO || insuficiente) begin
            $display("SECADO: %b,\n LAVADO: %b,\n LAVADO_PESADO: %b\n, insuficiente: %b\n\n",SECADO, LAVADO, LAVADO_PESADO, insuficiente);
       end 
    end

endmodule

tarea1_mod/tb.vcd
$date
	Sat Apr  6 22:40:56 2024
$end
$version
	Icarus Verilog
$end
$timescale
	1ns
$end
$scope module testbench $end
$var wire 1 ! rst $end
$var wire 1 " intro_moneda $end
$var wire 1 # insuficiente $end
$var wire 1 $ finalizar_pago $end
$var wire 1 % clk $end
$var wire 1 & SECADO $end
$var wire 1 ' LAVADO_PESADO $end
$var wire 1 ( LAVADO $end
$scope module lavanderia $end
$var wire 1 ! rst $end
$var wire 1 " intro_moneda $end
$var wire 1 $ finalizar_pago $end
$var wire 1 % clk $end
$var reg 1 ( LAVADO $end
$var reg 1 ' LAVADO_PESADO $end
$var reg 1 & SECADO $end
$var reg 4 ) count [3:0] $end
$var reg 1 # insuficiente $end
$var reg 2 * state [1:0] $end
$upscope $end
$scope module test $end
$var wire 1 + insuficiente $end
$var wire 1 , SECADO $end
$var wire 1 - LAVADO_PESADO $end
$var wire 1 . LAVADO $end
$var reg 1 % clk $end
$var reg 1 $ finalizar_pago $end
$var reg 1 " intro_moneda $end
$var reg 1 ! rst $end
$scope module lavanderia $end
$var wire 1 % clk $end
$var wire 1 $ finalizar_pago $end
$var wire 1 " intro_moneda $end
$var wire 1 ! rst $end
$var reg 1 . LAVADO $end
$var reg 1 - LAVADO_PESADO $end
$var reg 1 , SECADO $end
$var reg 4 / count [3:0] $end
$var reg 1 + insuficiente $end
$var reg 2 0 state [1:0] $end
$upscope $end
$upscope $end
$upscope $end
$enddefinitions $end
#0
$dumpvars
bx 0
bx /
x.
x-
x,
x+
bx *
bx )
x(
x'
x&
0%
0$
x#
0"
1!
$end
#5
0#
0'
0(
0&
b0 *
b0 )
0+
0-
0.
0,
b0 0
b0 /
1%
#10
0%
0!
#15
1%
#20
0%
#25
b1 )
b1 *
b1 /
b1 0
1%
1"
#30
0%
0"
#35
b10 /
b10 )
1%
1"
#40
0%
0"
#45
b11 )
b11 /
1%
1"
#50
0%
1$
0"
#55
b10 0
b10 *
1%
#60
0%
0$
#65
1&
1,
1%
#70
0%
#75
1%
#80
0%
#85
1%
#90
0%
#95
1%
#100
0%
#105
1%
#110
0%
#115
1%
#120
0%
#125
1%
1"
#130
0%
0"
#135
1%
1"
#140
0%
0"
#145
1%
1"
#150
0%
0"
#155
1%
1"
#160
0%
0"
#165
1%
1"
#170
0%
0"
#175
1%
1"
#180
0%
0"
#185
1%
1"
#190
0%
0"
#195
1%
1"
#200
0%
0"
#205
1%
1"
#210
0%
1$
0"
#215
1%
#220
0%
0$
#225
1%
#230
0%
#235
1%
#240
0%
#245
1%
#250
0%
#255
1%
#260
0%
#265
1%
#270
0%
#275
1%
#280
0%
#285
1%
1"
#290
0%
0"
#295
1%
1"
#300
0%
1$
0"
#305
1%
#310
0%
0$
