contador/tester.v
module tester(
    output reg clk,     // Entrada de reloj
    output reg reset,   // Entrada de reset
    output reg enable,
    input rco,
    input [3:0] count  // Salida del contador de 4 bits
);

always begin
    #2 clk = !clk;
end

initial begin
    reset = 1;
    clk = 0;
    enable = 0;

    #6;

    reset = 0;
    enable = 1;

    #80;

    $finish;
end





endmodule

contador/FF.v
module flipflop_D #(parameter N = 1)
(
    input clk,     // Entrada de reloj
    input reset,   // Entrada de reset asincrónico
    input [N-1:0] d,       // Entrada de datos
    output reg [N-1:0] q   // Salida del flip-flop
);

// Proceso de flip-flop tipo D
always @(posedge clk)
begin
    if (reset)
        q <= 1'b0; // Si se activa el reset, la salida se pone en 0
    else
        q <= d;    // Si no hay reset, la salida sigue el valor de la entrada d en cada flanco de subida del reloj
end

endmodule

contador/contador.v
`include "FF.v"

module contador(
    input clk,     // Entrada de reloj
    input reset,   // Entrada de reset
    input enable,
    output rco,
    output [3:0] count  // Salida del contador de 4 bits
);

reg [4:0] intern_count;

// Instanciación del flip-flop tipo D
flipflop_D #(.N(4)) D_FF4(.clk(clk), .reset(reset), .d(intern_count[3:0]), .q(count[3:0]));
flipflop_D DFF1(.clk(clk), .reset(reset), .d(intern_count[4]), .q(rco)); // Esta línea no cambió

// Proceso de conteo
always @(posedge clk or posedge reset)
begin
    if (reset) // Si el reset está activado
        intern_count <= 0;   // Reiniciar el contador a 0
    else if (enable) // Si el enable está activado
        intern_count <= intern_count + 1;   // Incrementar el contador
end

endmodule

contador/testbench.v
/* 
Material Circuitos Digitales 2

Archivo: testbench.v 

Descripcion: Testbench del contador.


    ----------                  -----------
    |           |               |         |
    |   TEST    | <---------->  |   DUT   |
    |           |               |         |
    ----------                  ----------

Autor: Ing. Ana Eugenia Sanchez Villalobos
*/

`include "contador.v"
`include "tester.v" //Tambien conocido como probador.


module testbench;
    wire clk, reset, enable, rco;
    wire [3:0] count;

    contador DUT(
        .clk(clk), 
        .enable(enable),
        .reset(reset), 
        .count(count[3:0]),
        .rco(rco)
    );

    // Instantiate the tester module
    tester test(
        .clk(clk), 
        .enable(enable),
        .reset(reset), 
        .count(count[3:0]),
        .rco(rco)
    );

    /* Para generar las ondas y
    y visualizar en gtkwave
    */
    initial begin
        $dumpfile("tb.vcd");
        $dumpvars;
    end

    //Mostrar los valores
    always @(posedge clk) begin
        $display("Valor del contador: %b", count);
        $display("Valor del contador: %b", rco);
    end

endmodule

contador/tb.vcd
$date
	Sat Apr  6 13:13:16 2024
$end
$version
	Icarus Verilog
$end
$timescale
	1s
$end
$scope module testbench $end
$var wire 1 ! reset $end
$var wire 1 " rco $end
$var wire 1 # enable $end
$var wire 4 $ count [3:0] $end
$var wire 1 % clk $end
$scope module DUT $end
$var wire 1 ! reset $end
$var wire 1 " rco $end
$var wire 1 # enable $end
$var wire 4 & count [3:0] $end
$var wire 1 % clk $end
$var reg 5 ' intern_count [4:0] $end
$scope module DFF1 $end
$var wire 1 ( d $end
$var wire 1 ! reset $end
$var wire 1 % clk $end
$var reg 1 " q $end
$upscope $end
$scope module D_FF4 $end
$var wire 4 ) d [3:0] $end
$var wire 1 ! reset $end
$var wire 1 % clk $end
$var reg 4 * q [3:0] $end
$upscope $end
$upscope $end
$scope module test $end
$var wire 4 + count [3:0] $end
$var wire 1 " rco $end
$var reg 1 % clk $end
$var reg 1 # enable $end
$var reg 1 ! reset $end
$upscope $end
$upscope $end
$enddefinitions $end
#0
$dumpvars
bx +
bx *
b0 )
0(
b0 '
bx &
0%
bx $
0#
x"
1!
$end
#2
b0 $
b0 &
b0 *
b0 +
0"
1%
#4
0%
#6
b1 )
b1 '
1%
1#
0!
#8
0%
#10
b10 )
b10 '
b1 $
b1 &
b1 *
b1 +
1%
#12
0%
#14
b11 )
b11 '
b10 $
b10 &
b10 *
b10 +
1%
#16
0%
#18
b100 )
b100 '
b11 $
b11 &
b11 *
b11 +
1%
#20
0%
#22
b101 )
b101 '
b100 $
b100 &
b100 *
b100 +
1%
#24
0%
#26
b110 )
b110 '
b101 $
b101 &
b101 *
b101 +
1%
#28
0%
#30
b111 )
b111 '
b110 $
b110 &
b110 *
b110 +
1%
#32
0%
#34
b1000 )
b1000 '
b111 $
b111 &
b111 *
b111 +
1%
#36
0%
#38
b1001 )
b1001 '
b1000 $
b1000 &
b1000 *
b1000 +
1%
#40
0%
#42
b1010 )
b1010 '
b1001 $
b1001 &
b1001 *
b1001 +
1%
#44
0%
#46
b1011 )
b1011 '
b1010 $
b1010 &
b1010 *
b1010 +
1%
#48
0%
#50
b1100 )
b1100 '
b1011 $
b1011 &
b1011 *
b1011 +
1%
#52
0%
#54
b1101 )
b1101 '
b1100 $
b1100 &
b1100 *
b1100 +
1%
#56
0%
#58
b1110 )
b1110 '
b1101 $
b1101 &
b1101 *
b1101 +
1%
#60
0%
#62
b1111 )
b1111 '
b1110 $
b1110 &
b1110 *
b1110 +
1%
#64
0%
#66
b0 )
1(
b10000 '
b1111 $
b1111 &
b1111 *
b1111 +
1%
#68
0%
#70
b1 )
b10001 '
1"
b0 $
b0 &
b0 *
b0 +
1%
#72
0%
#74
b10 )
b10010 '
b1 $
b1 &
b1 *
b1 +
1%
#76
0%
#78
b11 )
b10011 '
b10 $
b10 &
b10 *
b10 +
1%
#80
0%
#82
b100 )
b10100 '
b11 $
b11 &
b11 *
b11 +
1%
#84
0%
#86
b101 )
b10101 '
b100 $
b100 &
b100 *
b100 +
1%
