proyecto/Receptor/rec_tester.v
/******************************
* Codigo del tester del receptor MDIO
*
*
*
*
*******************************/

`timescale 1ns/1ns

module Tester_Receptor (
    output reg MDC, 
    output reg RESET,
    output reg MDIO_OUT,
    output reg MDIO_OE,
    output reg [15:0] RD_DATA,
    input MDIO_DONE,
    input MDIO_IN,
    input [4:0] ADDR,
    input [15:0] WR_DATA,
    input WR_STB //
);

// Generacion de reloj MDC
always begin 
    #5 MDC = !MDC; 
end

// // Inicializacion de señales de MDC (clock) y reset
// initial begin
//     MDC = 0;
//     RESET = 1;
// end

initial begin
    // Inicializacion de señales de MDC (clock) y reset
    MDC = 0;
    RESET = 0;
    MDIO_OUT = 0;
    MDIO_OE = 0;
    #10 

    // Coloca los datos de lectura iniciales
    RD_DATA = 16'h8FF1;
    RESET = 1'b1;
    #20
    MDIO_OE = 1;
    MDIO_OUT = 1;
    #10

    // Prueba de Transaccion de Lectura
    #10
    // Enviar datos por MDIO_OUT y verificar MDIO_IN
    MDIO_OUT = 1'b1;    // Envia 1 bit 
    #10
    MDIO_OUT = 1'b0;    // Envia 2 bit 
    #10
    MDIO_OUT = 1'b0;    // Envia 3 bit 
    #10
    MDIO_OUT = 1'b0;
    #10

    #670
    MDIO_OE = 0;        // Deshabilita la salida MDIO

    // Prueba de Transaccion de Escritura
    #20
    MDIO_OE = 1;        // Habilita MDIO para escritura
    MDIO_OUT = 1'b0;       // Envia datos para escritura
    #10
    MDIO_OUT = 1'b0;
    #10
    MDIO_OUT = 1'b0;
    #10
    MDIO_OUT = 1'b1;
    #10

    #670
    RESET = 0;
    #200
    $finish;
end
    
endmodule

proyecto/Receptor/Receptor.v
/******************************
* Codigo de receptor MDIO
*
*
*
*
*******************************/

// No funka del todo bien

module receptor_mdio(
    input MDC,
    input RESET,
    input MDIO_OUT,
    input MDIO_OE,
    input [15:0] RD_DATA,
    output reg MDIO_DONE,
    output reg MDIO_IN,
    output reg [4:0] ADDR,
    output reg [15:0] WR_DATA,
    output reg WR_STB   // Indica que los datos de WR_DATA y ADDR son validos
);

// Parametros locales para los estados de la FSM usando OneHot
localparam  IDLE = 4'b0000,    // Estado base (ground state)
            START = 4'b0001,   // Estado de Inicio/espera
            WRITE = 4'b0010,  // Estado de escritura
            READ = 4'b0100,   // Estado de lectura
            DONE = 4'b1000;   // Estado de transaccion completada

// Variables internas para la FSM
reg [3:0] state;
reg [5:0] data_counter;
reg [31:0] shift_reg; // Reg de desplazameinto para guardar los bits de entrada
reg internal_rst = 0;     // Señal de reinicio interno

// Variables intenas para las posiciones del frame format de Basic MDIO
reg [1:0] ST, OP, TA;
reg [4:0] PHYADDR, REGADDR;
reg [15:0] DATA;

// Asignacion de posiciones del frame format de Basic MDIO
always @(*) begin
    ST = shift_reg[31:30];
    OP = shift_reg[29:28];
    PHYADDR = shift_reg[27:23];
    REGADDR = shift_reg[22:18];
    TA = shift_reg[17:16];
    DATA = shift_reg[15:0];

    if (!RESET || internal_rst) begin
        // Se reinician de todas las señales
        state <= IDLE;
        MDIO_DONE <= 0;
        MDIO_IN <= 0;
        ADDR <= 0;
        WR_DATA <= 0;
        WR_STB <= 0;
        data_counter <= 0;
        internal_rst <= 0;
    end
end

always @(posedge MDC)begin
    if (state == IDLE && (OP == 2'b00 || OP == 2'b01))
        state <= START;
end

always @(posedge MDC) begin
        // Logica de la FSM
        case (state)
            // Estado de Inicio
            START: begin
                if (MDIO_OE) begin
                    shift_reg <= {shift_reg[31:0], MDIO_OUT};   // Desplaza bits de MDIO Out al registro
                    data_counter <= data_counter + 1;
                    if (data_counter == 31) begin
                        // Proximo estado basado en el tipo de OP
                        state <= (OP == 2'b01) ? WRITE : READ;
                        ADDR <= PHYADDR;  // Asigna la dir desde el registro de desplazamiento
                        WR_DATA <= DATA;  // Asigna datos de escritura desde el registro de desplazamiento
                        data_counter <= 0;
                    end
                end
            end
            // Estado de escritura
            WRITE: begin
                WR_STB <= 1;  // Indica datos son validos para Write
                MDIO_DONE <= 1; 
                state <= DONE;  // Pasa al estado de transaccion completada
            end
            // Estado de lectura
            READ: begin
                MDIO_IN <= RD_DATA[15 - data_counter];  // Enviar datos de lectura desde RD_DATA
                data_counter <= data_counter + 1;
                if (data_counter == 15) begin
                    MDIO_DONE <= 1;
                    state <= DONE;
                end
            end
            // Estado de transaccion completada
            DONE: begin
                WR_STB <= 0;  // Desactiva señal de escritra
                MDIO_DONE <= 0; // Desactiva señal de transac completada
                state <= IDLE;  // Pasa a estado de base
                internal_rst <= 1;
            end
            // Estado por default
            default: state = START;
        endcase
    end


endmodule

proyecto/Receptor/rec_tb.v
/******************************
* Codigo del testbench del receptor MDIO
*
*
*
*
*******************************/

`timescale 1ns/1ns

`include "Receptor.v"
`include "rec_tester.v"

module tb_Receptor;
    wire MDC;
    wire RESET;
    wire MDIO_OUT;
    wire MDIO_OE;
    wire MDIO_DONE;
    wire MDIO_IN;
    wire [4:0] ADDR;
    wire [15:0] WR_DATA;
    wire [15:0] RD_DATA;
    wire WR_STB;

    // Instancia del modulo Receptor
    receptor_mdio receptor (
        .MDC(MDC),
        .RESET(RESET),
        .MDIO_OUT(MDIO_OUT),
        .MDIO_OE(MDIO_OE),
        .MDIO_DONE(MDIO_DONE),
        .MDIO_IN(MDIO_IN),
        .ADDR(ADDR),
        .WR_DATA(WR_DATA),
        .RD_DATA(RD_DATA),
        .WR_STB(WR_STB)
    );

    // Instancia del modulo Tester
    Tester_Receptor prueba (
        .MDC(MDC),
        .RESET(RESET),
        .MDIO_OUT(MDIO_OUT),
        .MDIO_OE(MDIO_OE),
        .MDIO_DONE(MDIO_DONE),
        .MDIO_IN(MDIO_IN),
        .ADDR(ADDR),
        .WR_DATA(WR_DATA),
        .RD_DATA(RD_DATA),
        .WR_STB(WR_STB)
    );

    initial begin
        
        $dumpfile("tb_receptor.vcd");
        $dumpvars;
    end


endmodule

proyecto/Receptor/tb_receptor.vcd
$date
	Mon Jul  1 20:07:22 2024
$end
$version
	Icarus Verilog
$end
$timescale
	1ns
$end
$scope module tb_Receptor $end
$var wire 1 ! WR_STB $end
$var wire 16 " WR_DATA [15:0] $end
$var wire 1 # RESET $end
$var wire 16 $ RD_DATA [15:0] $end
$var wire 1 % MDIO_OUT $end
$var wire 1 & MDIO_OE $end
$var wire 1 ' MDIO_IN $end
$var wire 1 ( MDIO_DONE $end
$var wire 1 ) MDC $end
$var wire 5 * ADDR [4:0] $end
$scope module prueba $end
$var wire 1 ! WR_STB $end
$var wire 16 + WR_DATA [15:0] $end
$var wire 1 ' MDIO_IN $end
$var wire 1 ( MDIO_DONE $end
$var wire 5 , ADDR [4:0] $end
$var reg 1 ) MDC $end
$var reg 1 & MDIO_OE $end
$var reg 1 % MDIO_OUT $end
$var reg 16 - RD_DATA [15:0] $end
$var reg 1 # RESET $end
$upscope $end
$scope module receptor $end
$var wire 1 ) MDC $end
$var wire 1 & MDIO_OE $end
$var wire 1 % MDIO_OUT $end
$var wire 16 . RD_DATA [15:0] $end
$var wire 1 # RESET $end
$var reg 5 / ADDR [4:0] $end
$var reg 16 0 DATA [15:0] $end
$var reg 1 ( MDIO_DONE $end
$var reg 1 ' MDIO_IN $end
$var reg 2 1 OP [1:0] $end
$var reg 5 2 PHYADDR [4:0] $end
$var reg 5 3 REGADDR [4:0] $end
$var reg 2 4 ST [1:0] $end
$var reg 2 5 TA [1:0] $end
$var reg 16 6 WR_DATA [15:0] $end
$var reg 1 ! WR_STB $end
$var reg 6 7 data_counter [5:0] $end
$var reg 1 8 internal_rst $end
$var reg 32 9 shift_reg [31:0] $end
$var reg 4 : state [3:0] $end
$upscope $end
$upscope $end
$enddefinitions $end
#0
$dumpvars
b0 :
bx 9
08
b0 7
b0 6
bx 5
bx 4
bx 3
bx 2
bx 1
bx 0
b0 /
bx .
bx -
b0 ,
b0 +
b0 *
0)
0(
0'
0&
0%
bx $
0#
b0 "
0!
$end
#5
b1 :
1)
#10
0)
1#
b1000111111110001 $
b1000111111110001 -
b1000111111110001 .
#15
1)
#20
0)
#25
1)
#30
0)
1%
1&
#35
bx1 0
b1 7
bx1 9
1)
#40
0)
#45
bx11 0
b10 7
bx11 9
1)
#50
0)
#55
bx111 0
b11 7
bx111 9
1)
#60
0)
0%
#65
bx1110 0
b100 7
bx1110 9
1)
#70
0)
#75
bx11100 0
b101 7
bx11100 9
1)
#80
0)
#85
bx111000 0
b110 7
bx111000 9
1)
#90
0)
#95
bx1110000 0
b111 7
bx1110000 9
1)
#100
0)
#105
bx11100000 0
b1000 7
bx11100000 9
1)
#110
0)
#115
bx111000000 0
b1001 7
bx111000000 9
1)
#120
0)
#125
bx1110000000 0
b1010 7
bx1110000000 9
1)
#130
0)
#135
bx11100000000 0
b1011 7
bx11100000000 9
1)
#140
0)
#145
bx111000000000 0
b1100 7
bx111000000000 9
1)
#150
0)
#155
bx1110000000000 0
b1101 7
bx1110000000000 9
1)
#160
0)
#165
bx11100000000000 0
b1110 7
bx11100000000000 9
1)
#170
0)
#175
bx111000000000000 0
b1111 7
bx111000000000000 9
1)
#180
0)
#185
b1110000000000000 0
b10000 7
bx1110000000000000 9
1)
#190
0)
#195
b1100000000000000 0
bx1 5
b10001 7
bx11100000000000000 9
1)
#200
0)
#205
b1000000000000000 0
b11 5
b10010 7
bx111000000000000000 9
1)
#210
0)
#215
b0 0
bx1 3
b10011 7
bx1110000000000000000 9
1)
#220
0)
#225
b10 5
bx11 3
b10100 7
bx11100000000000000000 9
1)
#230
0)
#235
b0 5
bx111 3
b10101 7
bx111000000000000000000 9
1)
#240
0)
#245
bx1110 3
b10110 7
bx1110000000000000000000 9
1)
#250
0)
#255
b11100 3
b10111 7
bx11100000000000000000000 9
1)
#260
0)
#265
b11000 3
bx1 2
b11000 7
bx111000000000000000000000 9
1)
#270
0)
#275
b10000 3
bx11 2
b11001 7
bx1110000000000000000000000 9
1)
#280
0)
#285
b0 3
bx111 2
b11010 7
bx11100000000000000000000000 9
1)
#290
0)
#295
bx1110 2
b11011 7
bx111000000000000000000000000 9
1)
#300
0)
#305
b11100 2
b11100 7
bx1110000000000000000000000000 9
1)
#310
0)
#315
b11000 2
bx1 1
b11101 7
bx11100000000000000000000000000 9
1)
#320
0)
#325
b10000 2
b11 1
b11110 7
bx111000000000000000000000000000 9
1)
#330
0)
#335
b0 2
bx1 4
b11111 7
bx1110000000000000000000000000000 9
1)
#340
0)
#345
b10 1
b11 4
b100 :
b0 7
b11100000000000000000000000000000 9
1)
#350
0)
#355
b1 7
1'
1)
#360
0)
#365
b10 7
0'
1)
#370
0)
#375
b11 7
1)
#380
0)
#385
b100 7
1)
#390
0)
#395
b101 7
1'
1)
#400
0)
#405
b110 7
1)
#410
0)
#415
b111 7
1)
#420
0)
#425
b1000 7
1)
#430
0)
#435
b1001 7
1)
#440
0)
#445
b1010 7
1)
#450
0)
#455
b1011 7
1)
#460
0)
#465
b1100 7
1)
#470
0)
#475
b1101 7
0'
1)
#480
0)
#485
b1110 7
1)
#490
0)
#495
b1111 7
1)
#500
0)
#505
b1000 :
1(
b10000 7
1'
1)
#510
0)
#515
b0 7
0'
08
b0 :
0(
1)
#520
0)
#525
b1 :
1)
#530
0)
#535
b0 1
b1 7
b11000000000000000000000000000000 9
1)
#540
0)
#545
b10 4
b10 7
b10000000000000000000000000000000 9
1)
#550
0)
#555
b0 4
b11 7
b0 9
1)
#560
0)
#565
b100 7
1)
#570
0)
#575
b101 7
1)
#580
0)
#585
b110 7
1)
#590
0)
#595
b111 7
1)
#600
0)
#605
b1000 7
1)
#610
0)
#615
b1001 7
1)
#620
0)
#625
b1010 7
1)
#630
0)
#635
b1011 7
1)
#640
0)
#645
b1100 7
1)
#650
0)
#655
b1101 7
1)
#660
0)
#665
b1110 7
1)
#670
0)
#675
b1111 7
1)
#680
0)
#685
b10000 7
1)
#690
0)
#695
b10001 7
1)
#700
0)
#705
b10010 7
1)
#710
0)
#715
b10011 7
1)
#720
0)
#725
b10100 7
1)
#730
0)
#735
b10101 7
1)
#740
0)
#745
b10110 7
1)
#750
0)
#755
b10111 7
1)
#760
0)
0&
#765
1)
#770
0)
#775
1)
#780
0)
1&
#785
b11000 7
1)
#790
0)
#795
b11001 7
1)
#800
0)
#805
b11010 7
1)
#810
0)
1%
#815
b1 0
b11011 7
b1 9
1)
#820
0)
#825
b11 0
b11100 7
b11 9
1)
#830
0)
#835
b111 0
b11101 7
b111 9
1)
#840
0)
#845
b1111 0
b11110 7
b1111 9
1)
#850
0)
#855
b11111 0
b11111 7
b11111 9
1)
#860
0)
#865
b111111 0
b11111 "
b11111 +
b11111 6
b100 :
b0 7
b111111 9
1)
#870
0)
#875
b1 7
1'
1)
#880
0)
#885
b10 7
0'
1)
#890
0)
#895
b11 7
1)
#900
0)
#905
b100 7
1)
#910
0)
#915
b101 7
1'
1)
#920
0)
#925
b110 7
1)
#930
0)
#935
b111 7
1)
#940
0)
#945
b1000 7
1)
#950
0)
#955
b1001 7
1)
#960
0)
#965
b1010 7
1)
#970
0)
#975
b1011 7
1)
#980
0)
#985
b1100 7
1)
#990
0)
#995
b1101 7
0'
1)
#1000
0)
#1005
b1110 7
1)
#1010
0)
#1015
b1111 7
1)
#1020
0)
#1025
b1000 :
1(
b10000 7
1'
1)
#1030
0)
#1035
b0 7
b0 "
b0 +
b0 6
0'
08
b0 :
0(
1)
#1040
0)
#1045
b1 :
1)
#1050
0)
#1055
b1111111 0
b1 7
b1111111 9
1)
#1060
0)
#1065
b11111111 0
b10 7
b11111111 9
1)
#1070
0)
#1075
b111111111 0
b11 7
b111111111 9
1)
#1080
0)
#1085
b1111111111 0
b100 7
b1111111111 9
1)
#1090
0)
#1095
b11111111111 0
b101 7
b11111111111 9
1)
#1100
0)
#1105
b111111111111 0
b110 7
b111111111111 9
1)
#1110
0)
#1115
b1111111111111 0
b111 7
b1111111111111 9
1)
#1120
0)
#1125
b11111111111111 0
b1000 7
b11111111111111 9
1)
#1130
0)
#1135
b111111111111111 0
b1001 7
b111111111111111 9
1)
#1140
0)
#1145
b1111111111111111 0
b1010 7
b1111111111111111 9
1)
#1150
0)
#1155
b1 5
b1011 7
b11111111111111111 9
1)
#1160
0)
#1165
b11 5
b1100 7
b111111111111111111 9
1)
#1170
0)
#1175
b1 3
b1101 7
b1111111111111111111 9
1)
#1180
0)
#1185
b11 3
b1110 7
b11111111111111111111 9
1)
#1190
0)
#1195
b111 3
b1111 7
b111111111111111111111 9
1)
#1200
0)
#1205
b1111 3
b10000 7
b1111111111111111111111 9
1)
#1210
0)
#1215
b11111 3
b10001 7
b11111111111111111111111 9
1)
#1220
0)
#1225
b1 2
b10010 7
b111111111111111111111111 9
1)
#1230
0)
#1235
b11 2
b10011 7
b1111111111111111111111111 9
1)
#1240
0)
#1245
b111 2
b10100 7
b11111111111111111111111111 9
1)
#1250
0)
#1255
b1111 2
b10101 7
b111111111111111111111111111 9
1)
#1260
0)
#1265
b11111 2
b10110 7
b1111111111111111111111111111 9
1)
#1270
0)
#1275
b1 1
b10111 7
b11111111111111111111111111111 9
1)
#1280
0)
#1285
b11 1
b11000 7
b111111111111111111111111111111 9
1)
#1290
0)
#1295
b1 4
b11001 7
b1111111111111111111111111111111 9
1)
#1300
0)
#1305
b11 4
b11010 7
b11111111111111111111111111111111 9
1)
#1310
0)
#1315
b11011 7
1)
#1320
0)
#1325
b11100 7
1)
#1330
0)
#1335
b11101 7
1)
#1340
0)
#1345
b11110 7
1)
#1350
0)
#1355
b11111 7
1)
#1360
0)
#1365
b1111111111111111 "
b1111111111111111 +
b1111111111111111 6
b11111 *
b11111 ,
b11111 /
b100 :
b0 7
1)
#1370
0)
#1375
b1 7
1'
1)
#1380
0)
#1385
b10 7
0'
1)
#1390
0)
#1395
b11 7
1)
#1400
0)
#1405
b100 7
1)
#1410
0)
#1415
b101 7
1'
1)
#1420
0)
#1425
b110 7
1)
#1430
0)
#1435
b111 7
1)
#1440
0)
#1445
b1000 7
1)
#1450
0)
#1455
b1001 7
1)
#1460
0)
#1465
b1010 7
1)
#1470
0)
#1475
b1011 7
1)
#1480
0)
#1485
b1100 7
1)
#1490
b0 7
b0 "
b0 +
b0 6
b0 *
b0 ,
b0 /
0'
b0 :
0)
0#
#1495
b1 :
1)
#1500
0)
#1505
b1 7
1)
#1510
0)
#1515
b10 7
1)
#1520
0)
#1525
b11 7
1)
#1530
0)
#1535
b100 7
1)
#1540
0)
#1545
b101 7
1)
#1550
0)
#1555
b110 7
1)
#1560
0)
#1565
b111 7
1)
#1570
0)
#1575
b1000 7
1)
#1580
0)
#1585
b1001 7
1)
#1590
0)
#1595
b1010 7
1)
#1600
0)
#1605
b1011 7
1)
#1610
0)
#1615
b1100 7
1)
#1620
0)
#1625
b1101 7
1)
#1630
0)
#1635
b1110 7
1)
#1640
0)
#1645
b1111 7
1)
#1650
0)
#1655
b10000 7
1)
#1660
0)
#1665
b10001 7
1)
#1670
0)
#1675
b10010 7
1)
#1680
0)
#1685
b10011 7
1)
#1690
0)
