proyecto/tester.v
`timescale 1ns/1ns

module Tester (
    output reg clk, 
    output reg rst,
    output reg MDIO_START,
    output reg [15:0] MDIO_IN,
    output reg [31:0] T_DATA,
    input [15:0] RD_DATA,
    input DATA_RDY,
    input MDC, 
    input MDIO_OE,
    input MDIO_OUT
);

always begin 
    #5 clk = !clk; 
end

initial begin
    clk = 0;
    rst = 1'b1;
end

initial begin
    #10 

    T_DATA = 32'h8A5AFF01;
    MDIO_IN = 16'h8FF1;
    rst = 1'b0;
    #20
    MDIO_START = 1;
    #10

    #670
    MDIO_START = 0;
    #20
    T_DATA = 32'h9A5AFF01;
    #20
    MDIO_START = 1;
    #10

    #670
    MDIO_START = 0;
    rst = 1;

    #200


    $finish;
end
    
    
endmodule

proyecto/generador.v
`timescale 1ns/1ns

module Generador (
    input clk, 
    input rst,
    input MDIO_START,
    input [15:0] MDIO_IN,
    input [31:0] T_DATA,
    output reg [15:0] RD_DATA,
    output reg DATA_RDY,
    output reg MDC, 
    output reg MDIO_OE,
    output reg MDIO_OUT
);

localparam  START = 4'b0001,
            // SELECT = 4'b0010,
            READ = 4'b0100,
            WRITE = 4'b1000;

reg mdc_counter = 0;
reg [5:0] data_counter = 0;
reg internal_rst = 0;

reg [1:0] ST, OP, TA;
reg [4:0] PHYADDR, REGADDR; 
reg [15:0] DATA; 

reg [3:0] STATE = 0;



always @(*) begin

    ST <= T_DATA[31:30];
    OP <= T_DATA[29:28];
    TA <= T_DATA[17:16];
    PHYADDR <= T_DATA[27:23];
    REGADDR <= T_DATA[22:18];
    DATA <= T_DATA[15:0];

    if (rst || internal_rst) begin
        RD_DATA <= 0;
        DATA_RDY <= 0;
        MDC <= 0;
        MDIO_OE <= 0;
        MDIO_OUT <= 0;
        internal_rst <= 0;
        STATE <= START;
        data_counter <= 0;
    end
end

// MDC clock
always @(posedge clk) begin
    mdc_counter += 1;
    MDC <= mdc_counter; 
end

always @(posedge MDC) begin

    case (STATE)
        START: begin
            if (MDIO_START == 1) begin
                STATE = (OP == 00) ? READ : WRITE;
            end
            else begin
                STATE = START;
            end
        end
        READ: begin
            MDIO_OUT = T_DATA[31-data_counter];
            MDIO_OE <= (data_counter < 16) ? 1 : 0;


            if (data_counter >= 16) begin
                RD_DATA[data_counter-16] <= MDIO_IN[data_counter-16];
            end


            data_counter += 1;
            if (data_counter > 32) begin
                DATA_RDY <= 1;
                #20
                internal_rst <= 1;
                STATE = START;
            end
            else begin
                STATE = READ;
            end
        end

        WRITE: begin
            MDIO_OUT = T_DATA[31-data_counter];
            MDIO_OE <= 1;
            data_counter += 1;

            if (data_counter > 32) begin
                MDIO_OE <= 0;
                internal_rst <= 1;
                STATE = START;
            end
            else begin
                STATE = WRITE;
            end            
        end 
        default: STATE = START;
    endcase
end    
endmodule

proyecto/testbench.v
`include "generador.v"
`include "tester.v"

module testbench;
    wire clk; 
    wire rst;
    wire MDIO_START;
    wire [15:0] MDIO_IN;
    wire [31:0] T_DATA;
    wire [15:0] RD_DATA;
    wire DATA_RDY;
    wire MDC; 
    wire MDIO_OE;
    wire MDIO_OUT;


Generador generador (
    .clk(clk),
    .rst(rst),
    .MDIO_START(MDIO_START),
    .MDIO_IN(MDIO_IN[15:0]),
    .T_DATA(T_DATA[31:0]),
    .RD_DATA(RD_DATA[15:0]),
    .DATA_RDY(DATA_RDY),
    .MDC(MDC),
    .MDIO_OE(MDIO_OE),
    .MDIO_OUT(MDIO_OUT)
);

Tester test (
    .clk(clk),
    .rst(rst),
    .MDIO_START(MDIO_START),
    .MDIO_IN(MDIO_IN[15:0]),
    .T_DATA(T_DATA[31:0]),
    .RD_DATA(RD_DATA[15:0]),
    .DATA_RDY(DATA_RDY),
    .MDC(MDC),
    .MDIO_OE(MDIO_OE),
    .MDIO_OUT(MDIO_OUT)
);


initial begin
    $dumpfile("tb.vcd");
    $dumpvars;
end


endmodule

proyecto/tb.vcd
$date
	Mon Jul  1 01:42:50 2024
$end
$version
	Icarus Verilog
$end
$timescale
	1ns
$end
$scope module testbench $end
$var wire 1 ! rst $end
$var wire 1 " clk $end
$var wire 32 # T_DATA [31:0] $end
$var wire 16 $ RD_DATA [15:0] $end
$var wire 1 % MDIO_START $end
$var wire 1 & MDIO_OUT $end
$var wire 1 ' MDIO_OE $end
$var wire 16 ( MDIO_IN [15:0] $end
$var wire 1 ) MDC $end
$var wire 1 * DATA_RDY $end
$scope module generador $end
$var wire 1 ! rst $end
$var wire 1 " clk $end
$var wire 32 + T_DATA [31:0] $end
$var wire 1 % MDIO_START $end
$var wire 16 , MDIO_IN [15:0] $end
$var reg 16 - DATA [15:0] $end
$var reg 1 * DATA_RDY $end
$var reg 1 ) MDC $end
$var reg 1 ' MDIO_OE $end
$var reg 1 & MDIO_OUT $end
$var reg 2 . OP [1:0] $end
$var reg 5 / PHYADDR [4:0] $end
$var reg 16 0 RD_DATA [15:0] $end
$var reg 5 1 REGADDR [4:0] $end
$var reg 2 2 ST [1:0] $end
$var reg 4 3 STATE [3:0] $end
$var reg 2 4 TA [1:0] $end
$var reg 6 5 data_counter [5:0] $end
$var reg 1 6 internal_rst $end
$var reg 1 7 mdc_counter $end
$upscope $end
$scope module test $end
$var wire 1 * DATA_RDY $end
$var wire 1 ) MDC $end
$var wire 1 ' MDIO_OE $end
$var wire 1 & MDIO_OUT $end
$var wire 16 8 RD_DATA [15:0] $end
$var reg 16 9 MDIO_IN [15:0] $end
$var reg 1 % MDIO_START $end
$var reg 32 : T_DATA [31:0] $end
$var reg 1 " clk $end
$var reg 1 ! rst $end
$upscope $end
$upscope $end
$enddefinitions $end
#0
$dumpvars
bx :
bx 9
b0 8
07
06
b0 5
bx 4
b0 3
bx 2
bx 1
b0 0
bx /
bx .
bx -
bx ,
bx +
0*
x)
bx (
0'
0&
x%
b0 $
bx #
0"
0!
$end
#5
b1 3
1)
17
1"
#10
b1111111100000001 -
b10110 1
b10100 /
b10 4
b0 .
b10 2
0"
1!
b1000111111110001 (
b1000111111110001 ,
b1000111111110001 9
b10001010010110101111111100000001 #
b10001010010110101111111100000001 +
b10001010010110101111111100000001 :
#15
0)
07
1"
#20
0"
#25
b100 3
1)
17
1"
#30
0"
1%
#35
0)
07
1"
#40
0"
0%
#45
1'
b1 5
1&
1)
17
1"
#50
0"
#55
0)
07
1"
#60
0"
#65
b10 5
0&
1)
17
1"
#70
0"
#75
0)
07
1"
#80
0"
#85
b11 5
1)
17
1"
#90
0"
#95
0)
07
1"
#100
0"
#105
b100 5
1)
17
1"
#110
0"
#115
0)
07
1"
#120
0"
#125
b101 5
1&
1)
17
1"
#130
0"
#135
0)
07
1"
#140
0"
#145
b110 5
0&
1)
17
1"
#150
0"
#155
0)
07
1"
#160
0"
#165
b111 5
1&
1)
17
1"
#170
0"
#175
0)
07
1"
#180
0"
#185
b1000 5
0&
1)
17
1"
#190
0"
#195
0)
07
1"
#200
0"
#205
b1001 5
1)
17
1"
#210
0"
#215
0)
07
1"
#220
0"
#225
b1010 5
1&
1)
17
1"
#230
0"
#235
0)
07
1"
#240
0"
#245
b1011 5
0&
1)
17
1"
#250
0"
#255
0)
07
1"
#260
0"
#265
b1100 5
1&
1)
17
1"
#270
0"
#275
0)
07
1"
#280
0"
#285
b1101 5
1)
17
1"
#290
0"
#295
0)
07
1"
#300
0"
#305
b1110 5
0&
1)
17
1"
#310
0"
#315
0)
07
1"
#320
0"
#325
b1111 5
1&
1)
17
1"
#330
0"
#335
0)
07
1"
#340
0"
#345
b10000 5
0&
1)
17
1"
#350
0"
#355
0)
07
1"
#360
0"
#365
b1 $
b1 0
b1 8
0'
b10001 5
1&
1)
17
1"
#370
0"
#375
0)
07
1"
#380
0"
#385
b10010 5
1)
17
1"
#390
0"
#395
0)
07
1"
#400
0"
#405
b10011 5
1)
17
1"
#410
0"
#415
0)
07
1"
#420
0"
#425
b10100 5
1)
17
1"
#430
0"
#435
0)
07
1"
#440
0"
#445
b10001 $
b10001 0
b10001 8
b10101 5
1)
17
1"
#450
0"
#455
0)
07
1"
#460
0"
#465
b110001 $
b110001 0
b110001 8
b10110 5
1)
17
1"
#470
0"
#475
0)
07
1"
#480
0"
#485
b1110001 $
b1110001 0
b1110001 8
b10111 5
1)
17
1"
#490
0"
#495
0)
07
1"
#500
0"
#505
b11110001 $
b11110001 0
b11110001 8
b11000 5
1)
17
1"
#510
0"
#515
0)
07
1"
#520
0"
#525
b111110001 $
b111110001 0
b111110001 8
b11001 5
0&
1)
17
1"
#530
0"
#535
0)
07
1"
#540
0"
#545
b1111110001 $
b1111110001 0
b1111110001 8
b11010 5
1)
17
1"
#550
0"
#555
0)
07
1"
#560
0"
#565
b11111110001 $
b11111110001 0
b11111110001 8
b11011 5
1)
17
1"
#570
0"
#575
0)
07
1"
#580
0"
#585
b111111110001 $
b111111110001 0
b111111110001 8
b11100 5
1)
17
1"
#590
0"
#595
0)
07
1"
#600
0"
#605
b11101 5
1)
17
1"
#610
0"
#615
0)
07
1"
#620
0"
#625
b11110 5
1)
17
1"
#630
0"
#635
0)
07
1"
#640
0"
#645
b11111 5
1)
17
1"
#650
0"
#655
0)
07
1"
#660
0"
#665
1*
b1000111111110001 $
b1000111111110001 0
b1000111111110001 8
b100000 5
1&
1)
17
1"
#670
0"
#675
0)
07
1"
#680
0"
#685
b0 5
0&
0*
b0 $
b0 0
b0 8
1)
06
17
1"
b100 3
#690
0"
#695
0)
07
1"
#700
0"
#705
1'
b1 5
1&
1)
17
1"
#710
0"
#715
0)
07
1"
#720
0"
#725
b10 5
0&
1)
17
1"
#730
b1 .
0"
b10011010010110101111111100000001 #
b10011010010110101111111100000001 +
b10011010010110101111111100000001 :
#735
0)
07
1"
#740
0"
#745
b11 5
1)
17
1"
#750
0"
1%
#755
0)
07
1"
#760
0"
0%
#765
b100 5
1&
1)
17
1"
#770
0"
#775
0)
07
1"
#780
0"
#785
b101 5
1)
17
1"
#790
0"
#795
0)
07
1"
#800
0"
#805
b110 5
0&
1)
17
1"
#810
0"
#815
0)
07
1"
#820
0"
#825
b111 5
1&
1)
17
1"
#830
0"
#835
0)
07
1"
#840
0"
#845
b1000 5
0&
1)
17
1"
#850
0"
#855
0)
07
1"
#860
0"
#865
b1001 5
1)
17
1"
#870
0"
#875
0)
07
1"
#880
0"
#885
b1010 5
1&
1)
17
1"
#890
0"
#895
0)
07
1"
#900
0"
#905
b1011 5
0&
1)
17
1"
#910
0"
#915
0)
07
1"
#920
0"
#925
b1100 5
1&
1)
17
1"
#930
0"
#935
0)
07
1"
#940
0"
#945
b1101 5
1)
17
1"
#950
0"
#955
0)
07
1"
#960
0"
#965
b1110 5
0&
1)
17
1"
#970
0"
#975
0)
07
1"
#980
0"
#985
b1111 5
1&
1)
17
1"
#990
0"
#995
0)
07
1"
#1000
0"
#1005
b10000 5
0&
1)
17
1"
#1010
0"
#1015
0)
07
1"
#1020
0"
#1025
b1 $
b1 0
b1 8
0'
b10001 5
1&
1)
17
1"
#1030
0"
#1035
0)
07
1"
#1040
0"
#1045
b10010 5
1)
17
1"
#1050
0"
#1055
0)
07
1"
#1060
0"
#1065
b10011 5
1)
17
1"
#1070
0"
#1075
0)
07
1"
#1080
0"
#1085
b10100 5
1)
17
1"
#1090
0"
#1095
0)
07
1"
#1100
0"
#1105
b10001 $
b10001 0
b10001 8
b10101 5
1)
17
1"
#1110
0"
#1115
0)
07
1"
#1120
0"
#1125
b110001 $
b110001 0
b110001 8
b10110 5
1)
17
1"
#1130
0"
#1135
0)
07
1"
#1140
0"
#1145
b1110001 $
b1110001 0
b1110001 8
b10111 5
1)
17
1"
#1150
0"
#1155
0)
07
1"
#1160
0"
#1165
b11110001 $
b11110001 0
b11110001 8
b11000 5
1)
17
1"
#1170
0"
#1175
0)
07
1"
#1180
0"
#1185
b111110001 $
b111110001 0
b111110001 8
b11001 5
0&
1)
17
1"
#1190
0"
#1195
0)
07
1"
#1200
0"
#1205
b1111110001 $
b1111110001 0
b1111110001 8
b11010 5
1)
17
1"
#1210
0"
#1215
0)
07
1"
#1220
0"
#1225
b11111110001 $
b11111110001 0
b11111110001 8
b11011 5
1)
17
1"
#1230
0"
#1235
0)
07
1"
#1240
0"
#1245
b111111110001 $
b111111110001 0
b111111110001 8
b11100 5
1)
17
1"
#1250
0"
#1255
0)
07
1"
#1260
0"
#1265
b11101 5
1)
17
1"
#1270
0"
#1275
0)
07
1"
#1280
0"
#1285
b11110 5
1)
17
1"
#1290
0"
#1295
0)
07
1"
#1300
0"
#1305
b11111 5
1)
17
1"
#1310
0"
#1315
0)
07
1"
#1320
0"
#1325
1*
b1000111111110001 $
b1000111111110001 0
b1000111111110001 8
b100000 5
1&
1)
17
1"
#1330
0"
#1335
0)
07
1"
#1340
0"
#1345
b0 5
0&
0*
b0 $
b0 0
b0 8
1)
06
17
1"
b1000 3
#1350
0"
#1355
0)
07
1"
#1360
0"
#1365
1'
b1 5
1&
1)
17
1"
#1370
0"
#1375
0)
07
1"
#1380
0"
#1385
b10 5
0&
1)
17
1"
#1390
0"
#1395
0)
07
1"
#1400
0"
#1405
b11 5
1)
17
1"
#1410
0"
#1415
0)
07
1"
#1420
0"
#1425
b100 5
1&
1)
17
1"
#1430
b0 5
0&
0'
0"
0!
#1435
0)
07
1"
#1440
0"
#1445
1'
b1 5
1&
1)
17
1"
#1450
0"
#1455
0)
07
1"
#1460
0"
#1465
b10 5
0&
1)
17
1"
#1470
0"
#1475
0)
07
1"
#1480
0"
#1485
b11 5
1)
17
1"
#1490
0"
#1495
0)
07
1"
#1500
0"
#1505
b100 5
1&
1)
17
1"
#1510
0"
#1515
0)
07
1"
#1520
0"
#1525
b101 5
1)
17
1"
#1530
0"
#1535
0)
07
1"
#1540
0"
#1545
b110 5
0&
1)
17
1"
#1550
0"
#1555
0)
07
1"
#1560
0"
#1565
b111 5
1&
1)
17
1"
#1570
0"
#1575
0)
07
1"
#1580
0"
#1585
b1000 5
0&
1)
17
1"
#1590
0"
#1595
0)
07
1"
#1600
0"
#1605
b1001 5
1)
17
1"
#1610
0"
#1615
0)
07
1"
#1620
0"
#1625
b1010 5
1&
1)
17
1"
